[{"date":"Thu, 23 Apr 2026 17:05:53 GMT","sloc":47,"lloc":34,"functions":0,"deliveredBugs":0.262,"maintainability":49.489,"lintErrors":[],"difficulty":6.573},{"date":"Fri, 01 May 2026 16:09:14 GMT","sloc":47,"lloc":34,"functions":0,"deliveredBugs":0.262,"maintainability":49.489,"lintErrors":[],"difficulty":6.573},{"date":"Fri, 01 May 2026 16:12:06 GMT","sloc":47,"lloc":34,"functions":0,"deliveredBugs":0.262,"maintainability":49.489,"lintErrors":[],"difficulty":6.573},{"date":"Fri, 01 May 2026 16:15:18 GMT","sloc":47,"lloc":34,"functions":0,"deliveredBugs":0.262,"maintainability":49.489,"lintErrors":[],"difficulty":6.573}]